{
  "config": "{\"version\":\"5.57\",\"themeCollection\":{\"baseTheme\":{\"name\":\"CY24SU08\",\"version\":\"5.57\",\"type\":2}},\"activeSectionIndex\":0,\"defaultDrillFilterOtherVisuals\":true,\"slowDataSourceSettings\":{\"isCrossHighlightingDisabled\":false,\"isSlicerSelectionsButtonEnabled\":false,\"isFilterSelectionsButtonEnabled\":false,\"isFieldWellButtonEnabled\":false,\"isApplyAllButtonEnabled\":false},\"linguisticSchemaSyncVersion\":2,\"settings\":{\"useNewFilterPaneExperience\":true,\"allowChangeFilterTypes\":true,\"useStylableVisualContainerHeader\":true,\"queryLimitOption\":6,\"exportDataMode\":1,\"useDefaultAggregateDisplayName\":true,\"useEnhancedTooltips\":true},\"objects\":{\"section\":[{\"properties\":{\"verticalAlignment\":{\"expr\":{\"Literal\":{\"Value\":\"'Top'\"}}}}}],\"outspacePane\":[{\"properties\":{\"expanded\":{\"expr\":{\"Literal\":{\"Value\":\"true\"}}}}}]}}",
  "layoutOptimization": 0,
  "resourcePackages": [
    {
      "resourcePackage": {
        "disabled": false,
        "items": [
          {
            "name": "CY24SU08",
            "path": "BaseThemes/CY24SU08.json",
            "type": 202
          }
        ],
        "name": "SharedResources",
        "type": 2
      }
    }
  ],
  "sections": [
    {
      "config": "{\"objects\":{\"filterCard\":[{\"properties\":{\"textSize\":{\"expr\":{\"Literal\":{\"Value\":\"16L\"}}}},\"selector\":{\"id\":\"Available\"}}]}}",
      "displayName": "Current FY",
      "displayOption": 1,
      "filters": "[]",
      "height": 720.00,
      "name": "2ff600732131d06868b3",
      "ordinal": 2,
      "visualContainers": [
        {
          "config": "{\"name\":\"fc918e9285aea2cc6073\",\"layouts\":[{\"id\":0,\"position\":{\"x\":9.448891554591802,\"y\":0,\"z\":0,\"width\":1033.708736072343,\"height\":634.9655124685692,\"tabOrder\":0}}],\"singleVisual\":{\"visualType\":\"clusteredColumnChart\",\"projections\":{\"Category\":[{\"queryRef\":\"Badges.Fiscal Year\",\"active\":true}],\"Y\":[{\"queryRef\":\"CountNonNull(Badges.Badge Name )\"}],\"Series\":[{\"queryRef\":\"Badges.Badge Name \"}]},\"prototypeQuery\":{\"Version\":2,\"From\":[{\"Name\":\"b\",\"Entity\":\"Badges\",\"Type\":0}],\"Select\":[{\"Column\":{\"Expression\":{\"SourceRef\":{\"Source\":\"b\"}},\"Property\":\"Fiscal Year\"},\"Name\":\"Badges.Fiscal Year\",\"NativeReferenceName\":\"Fiscal Year\"},{\"Aggregation\":{\"Expression\":{\"Column\":{\"Expression\":{\"SourceRef\":{\"Source\":\"b\"}},\"Property\":\"Badge Name \"}},\"Function\":5},\"Name\":\"CountNonNull(Badges.Badge Name )\",\"NativeReferenceName\":\"Count of Badge Name \"},{\"Column\":{\"Expression\":{\"SourceRef\":{\"Source\":\"b\"}},\"Property\":\"Badge Name \"},\"Name\":\"Badges.Badge Name \",\"NativeReferenceName\":\"Badge Name \"}],\"OrderBy\":[{\"Direction\":2,\"Expression\":{\"Aggregation\":{\"Expression\":{\"Column\":{\"Expression\":{\"SourceRef\":{\"Source\":\"b\"}},\"Property\":\"Badge Name \"}},\"Function\":5}}}]},\"drillFilterOtherVisuals\":true,\"hasDefaultSort\":true,\"objects\":{\"labels\":[{\"properties\":{\"show\":{\"expr\":{\"Literal\":{\"Value\":\"true\"}}},\"enableTitleDataLabel\":{\"expr\":{\"Literal\":{\"Value\":\"true\"}}},\"enableValueDataLabel\":{\"expr\":{\"Literal\":{\"Value\":\"true\"}}},\"labelPosition\":{\"expr\":{\"Literal\":{\"Value\":\"'InsideEnd'\"}}},\"labelOrientation\":{\"expr\":{\"Literal\":{\"Value\":\"1D\"}}}}}],\"dataPoint\":[{\"properties\":{\"borderShow\":{\"expr\":{\"Literal\":{\"Value\":\"false\"}}}}}],\"legend\":[{\"properties\":{\"fontSize\":{\"expr\":{\"Literal\":{\"Value\":\"14D\"}}},\"showGradientLegend\":{\"expr\":{\"Literal\":{\"Value\":\"true\"}}},\"show\":{\"expr\":{\"Literal\":{\"Value\":\"true\"}}}}}]},\"vcObjects\":{\"subTitle\":[{\"properties\":{\"show\":{\"expr\":{\"Literal\":{\"Value\":\"false\"}}}}}],\"title\":[{\"properties\":{\"fontSize\":{\"expr\":{\"Literal\":{\"Value\":\"18D\"}}},\"text\":{\"expr\":{\"Literal\":{\"Value\":\"'Badge Report for FY25'\"}}},\"heading\":{\"expr\":{\"Literal\":{\"Value\":\"'Heading3'\"}}}}}],\"padding\":[{\"properties\":{\"top\":{\"expr\":{\"Literal\":{\"Value\":\"10D\"}}},\"left\":{\"expr\":{\"Literal\":{\"Value\":\"10D\"}}}}}]}}}",
          "filters": "[{\"name\":\"b83353b2b381313eab14\",\"expression\":{\"Column\":{\"Expression\":{\"SourceRef\":{\"Entity\":\"Badges\"}},\"Property\":\"Fiscal Year\"}},\"filter\":{\"Version\":2,\"From\":[{\"Name\":\"b\",\"Entity\":\"Badges\",\"Type\":0}],\"Where\":[{\"Condition\":{\"In\":{\"Expressions\":[{\"Column\":{\"Expression\":{\"SourceRef\":{\"Source\":\"b\"}},\"Property\":\"Fiscal Year\"}}],\"Values\":[[{\"Literal\":{\"Value\":\"2025L\"}}]]}}}]},\"type\":\"Categorical\",\"howCreated\":0,\"objects\":{},\"isHiddenInViewMode\":false}]",
          "height": 634.97,
          "width": 1033.71,
          "x": 9.45,
          "y": 0.00,
          "z": 0.00
        }
      ],
      "width": 1280.00
    },
    {
      "config": "{}",
      "displayName": "All Year",
      "displayOption": 1,
      "filters": "[]",
      "height": 720.00,
      "name": "8e8a0b07c60967e93b0a",
      "ordinal": 1,
      "visualContainers": [
        {
          "config": "{\"name\":\"a8e3b4b9dd269d1ca6db\",\"layouts\":[{\"id\":0,\"position\":{\"x\":9.253360442787756,\"y\":0,\"z\":0,\"width\":1013.2429684852593,\"height\":624.6018298881735,\"tabOrder\":0}}],\"singleVisual\":{\"visualType\":\"clusteredColumnChart\",\"projections\":{\"Category\":[{\"queryRef\":\"Badges.Fiscal Year\",\"active\":true}],\"Series\":[{\"queryRef\":\"Badges.Badge Name \"}],\"Y\":[{\"queryRef\":\"CountNonNull(Badges.Badge Name )\"}]},\"prototypeQuery\":{\"Version\":2,\"From\":[{\"Name\":\"b\",\"Entity\":\"Badges\",\"Type\":0}],\"Select\":[{\"Column\":{\"Expression\":{\"SourceRef\":{\"Source\":\"b\"}},\"Property\":\"Fiscal Year\"},\"Name\":\"Badges.Fiscal Year\",\"NativeReferenceName\":\"Fiscal Year\"},{\"Column\":{\"Expression\":{\"SourceRef\":{\"Source\":\"b\"}},\"Property\":\"Badge Name \"},\"Name\":\"Badges.Badge Name \",\"NativeReferenceName\":\"Badge Name \"},{\"Aggregation\":{\"Expression\":{\"Column\":{\"Expression\":{\"SourceRef\":{\"Source\":\"b\"}},\"Property\":\"Badge Name \"}},\"Function\":5},\"Name\":\"CountNonNull(Badges.Badge Name )\",\"NativeReferenceName\":\"Count of Badge Name \"}]},\"queryOptions\":{\"keepProjectionOrder\":true},\"showAllRoles\":[\"Series\"],\"drillFilterOtherVisuals\":true,\"objects\":{\"labels\":[{\"properties\":{\"show\":{\"expr\":{\"Literal\":{\"Value\":\"true\"}}},\"enableTitleDataLabel\":{\"expr\":{\"Literal\":{\"Value\":\"true\"}}},\"labelPosition\":{\"expr\":{\"Literal\":{\"Value\":\"'InsideEnd'\"}}},\"showBlankAs\":{\"expr\":{\"Literal\":{\"Value\":\"'0'\"}}},\"enableBackground\":{\"expr\":{\"Literal\":{\"Value\":\"false\"}}},\"labelOverflow\":{\"expr\":{\"Literal\":{\"Value\":\"false\"}}},\"enableDetailDataLabel\":{\"expr\":{\"Literal\":{\"Value\":\"false\"}}}}},{\"properties\":{},\"selector\":{\"data\":[{\"dataViewWildcard\":{\"matchingOption\":1}}],\"highlightMatching\":1}}],\"valueAxis\":[{\"properties\":{}}],\"categoryAxis\":[{\"properties\":{\"axisType\":{\"expr\":{\"Literal\":{\"Value\":\"'Categorical'\"}}}}}]}}}",
          "filters": "[]",
          "height": 624.60,
          "width": 1013.24,
          "x": 9.25,
          "y": 0.00,
          "z": 0.00
        }
      ],
      "width": 1280.00
    },
    {
      "config": "{\"objects\":{\"background\":[{\"properties\":{\"color\":{\"solid\":{\"color\":{\"expr\":{\"Literal\":{\"Value\":\"'#FFFFFF'\"}}}}},\"transparency\":{\"expr\":{\"Literal\":{\"Value\":\"100D\"}}}}}]}}",
      "displayName": "Badge Report",
      "displayOption": 1,
      "filters": "[]",
      "height": 720.00,
      "name": "e5b44e94c74c2062615d",
      "visualContainers": [
        {
          "config": "{\"name\":\"06a9943667cb410d836b\",\"layouts\":[{\"id\":0,\"position\":{\"x\":0,\"y\":514.9146110056926,\"z\":0,\"width\":770.752688172043,\"height\":205.64199873497788,\"tabOrder\":0}}],\"singleVisual\":{\"visualType\":\"pivotTable\",\"projections\":{\"Rows\":[{\"queryRef\":\"Badges.Name\",\"active\":true}],\"Columns\":[{\"queryRef\":\"Badges.Badge Name \",\"active\":true}],\"Values\":[{\"queryRef\":\"Min(Badges.Badge Name )\"}]},\"prototypeQuery\":{\"Version\":2,\"From\":[{\"Name\":\"b\",\"Entity\":\"Badges\",\"Type\":0}],\"Select\":[{\"Column\":{\"Expression\":{\"SourceRef\":{\"Source\":\"b\"}},\"Property\":\"Name\"},\"Name\":\"Badges.Name\",\"NativeReferenceName\":\"Name\"},{\"Column\":{\"Expression\":{\"SourceRef\":{\"Source\":\"b\"}},\"Property\":\"Badge Name \"},\"Name\":\"Badges.Badge Name \",\"NativeReferenceName\":\"Badge Name \"},{\"Aggregation\":{\"Expression\":{\"Column\":{\"Expression\":{\"SourceRef\":{\"Source\":\"b\"}},\"Property\":\"Badge Name \"}},\"Function\":5},\"Name\":\"Min(Badges.Badge Name )\",\"NativeReferenceName\":\"Count of Badge Name \"}],\"OrderBy\":[{\"Direction\":2,\"Expression\":{\"Aggregation\":{\"Expression\":{\"Column\":{\"Expression\":{\"SourceRef\":{\"Source\":\"b\"}},\"Property\":\"Badge Name \"}},\"Function\":5}}}]},\"drillFilterOtherVisuals\":true,\"objects\":{\"values\":[{\"properties\":{\"fontSize\":{\"expr\":{\"Literal\":{\"Value\":\"12D\"}}},\"backColorPrimary\":{\"solid\":{\"color\":{\"expr\":{\"Literal\":{\"Value\":\"'#9CEAEB'\"}}}}},\"backColorSecondary\":{\"solid\":{\"color\":{\"expr\":{\"Literal\":{\"Value\":\"'#D8F5AF'\"}}}}},\"bandedRowHeaders\":{\"expr\":{\"Literal\":{\"Value\":\"true\"}}},\"valuesOnRow\":{\"expr\":{\"Literal\":{\"Value\":\"false\"}}}}}],\"columnHeaders\":[{\"properties\":{\"fontSize\":{\"expr\":{\"Literal\":{\"Value\":\"15D\"}}},\"bold\":{\"expr\":{\"Literal\":{\"Value\":\"true\"}}},\"alignment\":{\"expr\":{\"Literal\":{\"Value\":\"'Left'\"}}}}}],\"rowHeaders\":[{\"properties\":{\"fontSize\":{\"expr\":{\"Literal\":{\"Value\":\"12D\"}}},\"steppedLayoutIndentation\":{\"expr\":{\"Literal\":{\"Value\":\"10D\"}}},\"wordWrap\":{\"expr\":{\"Literal\":{\"Value\":\"true\"}}}}}],\"grid\":[{\"properties\":{\"gridHorizontal\":{\"expr\":{\"Literal\":{\"Value\":\"true\"}}},\"outlineStyle\":{\"expr\":{\"Literal\":{\"Value\":\"15D\"}}},\"gridVertical\":{\"expr\":{\"Literal\":{\"Value\":\"true\"}}},\"gridHorizontalWeight\":{\"expr\":{\"Literal\":{\"Value\":\"1D\"}}},\"rowPadding\":{\"expr\":{\"Literal\":{\"Value\":\"2D\"}}},\"imageHeight\":{\"expr\":{\"Literal\":{\"Value\":\"75D\"}}},\"outlineColor\":{\"solid\":{\"color\":{\"expr\":{\"ThemeDataColor\":{\"ColorId\":1,\"Percent\":0}}}}},\"outlineWeight\":{\"expr\":{\"Literal\":{\"Value\":\"1D\"}}},\"gridHorizontalColor\":{\"solid\":{\"color\":{\"expr\":{\"ThemeDataColor\":{\"ColorId\":1,\"Percent\":0}}}}},\"gridVerticalColor\":{\"solid\":{\"color\":{\"expr\":{\"ThemeDataColor\":{\"ColorId\":1,\"Percent\":0}}}}}}}],\"general\":[{\"properties\":{\"layout\":{\"expr\":{\"Literal\":{\"Value\":\"'Compact'\"}}}}}],\"blankRows\":[{\"properties\":{\"showBlankRows\":{\"expr\":{\"Literal\":{\"Value\":\"false\"}}}}}],\"columnWidth\":[{\"properties\":{\"value\":{\"expr\":{\"Literal\":{\"Value\":\"118.33838268027517D\"}}}},\"selector\":{\"data\":[{\"total\":[{\"Column\":{\"Expression\":{\"SourceRef\":{\"Entity\":\"Badges\"}},\"Property\":\"Badge Name \"}}]}]}}]},\"vcObjects\":{\"padding\":[{\"properties\":{\"top\":{\"expr\":{\"Literal\":{\"Value\":\"10D\"}}},\"left\":{\"expr\":{\"Literal\":{\"Value\":\"10D\"}}}}}]}}}",
          "filters": "[]",
          "height": 205.64,
          "width": 770.75,
          "x": 0.00,
          "y": 514.91,
          "z": 0.00
        },
        {
          "config": "{\"name\":\"36a94874e1f20b44e606\",\"layouts\":[{\"id\":0,\"position\":{\"x\":0,\"y\":171.63820366856422,\"z\":1000,\"width\":820.9487666034156,\"height\":310.8918406072106,\"tabOrder\":1000}}],\"singleVisual\":{\"visualType\":\"pivotTable\",\"projections\":{\"Rows\":[{\"queryRef\":\"Badges.Department\",\"active\":true}],\"Columns\":[{\"queryRef\":\"Badges.Badge Name \",\"active\":true}],\"Values\":[{\"queryRef\":\"Min(Badges.Badge Name )\"}]},\"prototypeQuery\":{\"Version\":2,\"From\":[{\"Name\":\"b\",\"Entity\":\"Badges\",\"Type\":0}],\"Select\":[{\"Column\":{\"Expression\":{\"SourceRef\":{\"Source\":\"b\"}},\"Property\":\"Department\"},\"Name\":\"Badges.Department\",\"NativeReferenceName\":\"Department\"},{\"Column\":{\"Expression\":{\"SourceRef\":{\"Source\":\"b\"}},\"Property\":\"Badge Name \"},\"Name\":\"Badges.Badge Name \",\"NativeReferenceName\":\"Badge Name \"},{\"Aggregation\":{\"Expression\":{\"Column\":{\"Expression\":{\"SourceRef\":{\"Source\":\"b\"}},\"Property\":\"Badge Name \"}},\"Function\":5},\"Name\":\"Min(Badges.Badge Name )\",\"NativeReferenceName\":\"Count of Badge Name \"}],\"OrderBy\":[{\"Direction\":1,\"Expression\":{\"Column\":{\"Expression\":{\"SourceRef\":{\"Source\":\"b\"}},\"Property\":\"Department\"}}}]},\"drillFilterOtherVisuals\":true,\"objects\":{\"values\":[{\"properties\":{\"fontSize\":{\"expr\":{\"Literal\":{\"Value\":\"15D\"}}},\"backColorPrimary\":{\"solid\":{\"color\":{\"expr\":{\"Literal\":{\"Value\":\"'#99C3F0'\"}}}}},\"backColorSecondary\":{\"solid\":{\"color\":{\"expr\":{\"ThemeDataColor\":{\"ColorId\":2,\"Percent\":0.2}}}}}}}],\"grid\":[{\"properties\":{\"gridHorizontal\":{\"expr\":{\"Literal\":{\"Value\":\"true\"}}},\"gridVertical\":{\"expr\":{\"Literal\":{\"Value\":\"true\"}}},\"rowPadding\":{\"expr\":{\"Literal\":{\"Value\":\"2D\"}}},\"outlineStyle\":{\"expr\":{\"Literal\":{\"Value\":\"15D\"}}},\"outlineWeight\":{\"expr\":{\"Literal\":{\"Value\":\"1D\"}}},\"outlineColor\":{\"solid\":{\"color\":{\"expr\":{\"ThemeDataColor\":{\"ColorId\":1,\"Percent\":0}}}}},\"gridHorizontalColor\":{\"solid\":{\"color\":{\"expr\":{\"ThemeDataColor\":{\"ColorId\":1,\"Percent\":0}}}}},\"gridVerticalColor\":{\"solid\":{\"color\":{\"expr\":{\"ThemeDataColor\":{\"ColorId\":1,\"Percent\":0}}}}}}}],\"columnHeaders\":[{\"properties\":{\"fontSize\":{\"expr\":{\"Literal\":{\"Value\":\"15D\"}}},\"bold\":{\"expr\":{\"Literal\":{\"Value\":\"true\"}}},\"wordWrap\":{\"expr\":{\"Literal\":{\"Value\":\"true\"}}},\"backColor\":{\"solid\":{\"color\":{\"expr\":{\"Literal\":{\"Value\":\"'#FFFFFF'\"}}}}},\"autoSizeColumnWidth\":{\"expr\":{\"Literal\":{\"Value\":\"true\"}}}}}],\"rowHeaders\":[{\"properties\":{\"fontSize\":{\"expr\":{\"Literal\":{\"Value\":\"15D\"}}},\"bold\":{\"expr\":{\"Literal\":{\"Value\":\"false\"}}},\"backColor\":{\"solid\":{\"color\":{\"expr\":{\"ThemeDataColor\":{\"ColorId\":0,\"Percent\":0}}}}}}}],\"columnWidth\":[{\"properties\":{},\"selector\":{\"data\":[{\"scopeId\":{\"Comparison\":{\"ComparisonKind\":0,\"Left\":{\"Column\":{\"Expression\":{\"SourceRef\":{\"Entity\":\"Badges\"}},\"Property\":\"Badge Name \"}},\"Right\":{\"Literal\":{\"Value\":\"'Platinum'\"}}}}}]}},{\"properties\":{},\"selector\":{\"data\":[{\"scopeId\":{\"Comparison\":{\"ComparisonKind\":0,\"Left\":{\"Column\":{\"Expression\":{\"SourceRef\":{\"Entity\":\"Badges\"}},\"Property\":\"Badge Name \"}},\"Right\":{\"Literal\":{\"Value\":\"'Gold'\"}}}}}]}},{\"properties\":{},\"selector\":{\"data\":[{\"scopeId\":{\"Comparison\":{\"ComparisonKind\":0,\"Left\":{\"Column\":{\"Expression\":{\"SourceRef\":{\"Entity\":\"Badges\"}},\"Property\":\"Badge Name \"}},\"Right\":{\"Literal\":{\"Value\":\"'Silver'\"}}}}}]}},{\"properties\":{},\"selector\":{\"data\":[{\"scopeId\":{\"Comparison\":{\"ComparisonKind\":0,\"Left\":{\"Column\":{\"Expression\":{\"SourceRef\":{\"Entity\":\"Badges\"}},\"Property\":\"Badge Name \"}},\"Right\":{\"Literal\":{\"Value\":\"'Bronze'\"}}}}}]}},{\"properties\":{},\"selector\":{\"data\":[{\"total\":[{\"Column\":{\"Expression\":{\"SourceRef\":{\"Entity\":\"Badges\"}},\"Property\":\"Badge Name \"}}]}]}},{\"properties\":{},\"selector\":{\"metadata\":\"Badges.Department\"}}],\"subTotals\":[{\"properties\":{\"columnSubtotals\":{\"expr\":{\"Literal\":{\"Value\":\"true\"}}},\"rowSubtotals\":{\"expr\":{\"Literal\":{\"Value\":\"true\"}}}}}],\"columnTotal\":[{\"properties\":{\"fontSize\":{\"expr\":{\"Literal\":{\"Value\":\"15D\"}}}}}]}}}",
          "filters": "[{\"name\":\"ae9b3e58719698ef0c01\",\"expression\":{\"Column\":{\"Expression\":{\"SourceRef\":{\"Entity\":\"Badges\"}},\"Property\":\"FY\"}},\"type\":\"Categorical\",\"howCreated\":1}]",
          "height": 310.89,
          "width": 820.95,
          "x": 0.00,
          "y": 171.64,
          "z": 1000.00
        },
        {
          "config": "{\"name\":\"61897a37e2dd81e9d7de\",\"layouts\":[{\"id\":0,\"position\":{\"x\":704.8873099725485,\"y\":66.14224088214262,\"z\":4000,\"width\":200.3165009573462,\"height\":49.13423608387737,\"tabOrder\":4000}}],\"singleVisual\":{\"visualType\":\"actionButton\",\"drillFilterOtherVisuals\":true,\"objects\":{\"icon\":[{\"properties\":{\"shapeType\":{\"expr\":{\"Literal\":{\"Value\":\"'clearAllSlicers'\"}}}},\"selector\":{\"id\":\"default\"}},{\"properties\":{\"show\":{\"expr\":{\"Literal\":{\"Value\":\"false\"}}}}}],\"text\":[{\"properties\":{\"show\":{\"expr\":{\"Literal\":{\"Value\":\"true\"}}}}},{\"properties\":{\"text\":{\"expr\":{\"Literal\":{\"Value\":\"'Clear all slicers'\"}}},\"horizontalAlignment\":{\"expr\":{\"Literal\":{\"Value\":\"'center'\"}}},\"fontSize\":{\"expr\":{\"Literal\":{\"Value\":\"14D\"}}},\"bold\":{\"expr\":{\"Literal\":{\"Value\":\"true\"}}},\"fontFamily\":{\"expr\":{\"Literal\":{\"Value\":\"'wf_standard-font, helvetica, arial, sans-serif'\"}}}},\"selector\":{\"id\":\"default\"}}]},\"vcObjects\":{\"visualLink\":[{\"properties\":{\"show\":{\"expr\":{\"Literal\":{\"Value\":\"true\"}}},\"type\":{\"expr\":{\"Literal\":{\"Value\":\"'ClearAllSlicers'\"}}},\"tooltipPlaceholderText\":{\"expr\":{\"Literal\":{\"Value\":\"'Clear all slicers on this page'\"}}}}}]}},\"howCreated\":\"InsertVisualButton\"}",
          "filters": "[]",
          "height": 49.13,
          "width": 200.32,
          "x": 704.89,
          "y": 66.14,
          "z": 4000.00
        },
        {
          "config": "{\"name\":\"a936f32979944e08fdc7\",\"layouts\":[{\"id\":0,\"position\":{\"x\":393.472485768501,\"y\":66.38836179633144,\"z\":3000,\"width\":262.31499051233396,\"height\":64.76913345983554,\"tabOrder\":3000}}],\"singleVisual\":{\"visualType\":\"slicer\",\"projections\":{\"Values\":[{\"queryRef\":\"Badges.Badge Type\",\"active\":true}]},\"prototypeQuery\":{\"Version\":2,\"From\":[{\"Name\":\"b\",\"Entity\":\"Badges\",\"Type\":0}],\"Select\":[{\"Column\":{\"Expression\":{\"SourceRef\":{\"Source\":\"b\"}},\"Property\":\"Badge Type\"},\"Name\":\"Badges.Badge Type\",\"NativeReferenceName\":\"Badge Type\"}]},\"drillFilterOtherVisuals\":true,\"objects\":{\"data\":[{\"properties\":{\"mode\":{\"expr\":{\"Literal\":{\"Value\":\"'Dropdown'\"}}}}}],\"header\":[{\"properties\":{\"textSize\":{\"expr\":{\"Literal\":{\"Value\":\"14D\"}}},\"bold\":{\"expr\":{\"Literal\":{\"Value\":\"true\"}}}}}],\"general\":[{\"properties\":{}}]}}}",
          "filters": "[]",
          "height": 64.77,
          "width": 262.31,
          "x": 393.47,
          "y": 66.39,
          "z": 3000.00
        },
        {
          "config": "{\"name\":\"ae581797d1480107aeea\",\"layouts\":[{\"id\":0,\"position\":{\"x\":46.957621758380775,\"y\":66.38836179633144,\"z\":2000,\"width\":328.7033523086654,\"height\":64.76913345983554,\"tabOrder\":2000}}],\"singleVisual\":{\"visualType\":\"slicer\",\"projections\":{\"Values\":[{\"queryRef\":\"Badges.Fiscal Year\",\"active\":true}]},\"prototypeQuery\":{\"Version\":2,\"From\":[{\"Name\":\"b\",\"Entity\":\"Badges\",\"Type\":0}],\"Select\":[{\"Column\":{\"Expression\":{\"SourceRef\":{\"Source\":\"b\"}},\"Property\":\"Fiscal Year\"},\"Name\":\"Badges.Fiscal Year\",\"NativeReferenceName\":\"Fiscal Year\"}]},\"drillFilterOtherVisuals\":true,\"objects\":{\"data\":[{\"properties\":{\"mode\":{\"expr\":{\"Literal\":{\"Value\":\"'Dropdown'\"}}}}}],\"general\":[{\"properties\":{}}],\"header\":[{\"properties\":{\"textSize\":{\"expr\":{\"Literal\":{\"Value\":\"14D\"}}},\"bold\":{\"expr\":{\"Literal\":{\"Value\":\"true\"}}},\"outlineStyle\":{\"expr\":{\"Literal\":{\"Value\":\"0D\"}}}}}]}}}",
          "filters": "[]",
          "height": 64.77,
          "width": 328.70,
          "x": 46.96,
          "y": 66.39,
          "z": 2000.00
        }
      ],
      "width": 1280.00
    },
    {
      "config": "{}",
      "displayName": "FY25 Pie Chart",
      "displayOption": 1,
      "filters": "[]",
      "height": 720.00,
      "name": "fc984c300ea95534a092",
      "ordinal": 3,
      "visualContainers": [
        {
          "config": "{\"name\":\"f6e6df49a3bb8702b861\",\"layouts\":[{\"id\":0,\"position\":{\"x\":32.12623128561213,\"y\":26.456896352857047,\"z\":0,\"width\":863.6286880896907,\"height\":487.56280421693697,\"tabOrder\":0}}],\"singleVisual\":{\"visualType\":\"pieChart\",\"projections\":{\"Category\":[{\"queryRef\":\"Badges.Badge Name \",\"active\":true}],\"Y\":[{\"queryRef\":\"CountNonNull(Badges.FY)\"}]},\"prototypeQuery\":{\"Version\":2,\"From\":[{\"Name\":\"b\",\"Entity\":\"Badges\",\"Type\":0}],\"Select\":[{\"Column\":{\"Expression\":{\"SourceRef\":{\"Source\":\"b\"}},\"Property\":\"Badge Name \"},\"Name\":\"Badges.Badge Name \",\"NativeReferenceName\":\"Badge Name \"},{\"Aggregation\":{\"Expression\":{\"Column\":{\"Expression\":{\"SourceRef\":{\"Source\":\"b\"}},\"Property\":\"FY\"}},\"Function\":5},\"Name\":\"CountNonNull(Badges.FY)\",\"NativeReferenceName\":\"Count of FY\"}]},\"drillFilterOtherVisuals\":true,\"objects\":{\"labels\":[{\"properties\":{\"position\":{\"expr\":{\"Literal\":{\"Value\":\"'inside'\"}}},\"labelStyle\":{\"expr\":{\"Literal\":{\"Value\":\"'Both'\"}}},\"labelDisplayUnits\":{\"expr\":{\"Literal\":{\"Value\":\"1D\"}}}}}]},\"vcObjects\":{\"title\":[{\"properties\":{\"text\":{\"expr\":{\"Literal\":{\"Value\":\"'FY25 Badge Report'\"}}},\"heading\":{\"expr\":{\"Literal\":{\"Value\":\"'Heading3'\"}}},\"alignment\":{\"expr\":{\"Literal\":{\"Value\":\"'center'\"}}},\"fontSize\":{\"expr\":{\"Literal\":{\"Value\":\"16D\"}}},\"titleWrap\":{\"expr\":{\"Literal\":{\"Value\":\"true\"}}},\"bold\":{\"expr\":{\"Literal\":{\"Value\":\"true\"}}}}}],\"spacing\":[{\"properties\":{\"verticalSpacing\":{\"expr\":{\"Literal\":{\"Value\":\"5D\"}}},\"customizeSpacing\":{\"expr\":{\"Literal\":{\"Value\":\"true\"}}},\"spaceBelowTitle\":{\"expr\":{\"Literal\":{\"Value\":\"4D\"}}}}}],\"general\":[{\"properties\":{\"keepLayerOrder\":{\"expr\":{\"Literal\":{\"Value\":\"false\"}}}}}],\"border\":[{\"properties\":{\"show\":{\"expr\":{\"Literal\":{\"Value\":\"true\"}}}}}],\"visualHeader\":[{\"properties\":{\"show\":{\"expr\":{\"Literal\":{\"Value\":\"true\"}}}}}],\"subTitle\":[{\"properties\":{\"show\":{\"expr\":{\"Literal\":{\"Value\":\"false\"}}}}}],\"padding\":[{\"properties\":{\"top\":{\"expr\":{\"Literal\":{\"Value\":\"10D\"}}}}}]}}}",
          "filters": "[{\"name\":\"616669938436e3ea5100\",\"expression\":{\"Column\":{\"Expression\":{\"SourceRef\":{\"Entity\":\"Badges\"}},\"Property\":\"FY\"}},\"filter\":{\"Version\":2,\"From\":[{\"Name\":\"b\",\"Entity\":\"Badges\",\"Type\":0}],\"Where\":[{\"Condition\":{\"In\":{\"Expressions\":[{\"Column\":{\"Expression\":{\"SourceRef\":{\"Source\":\"b\"}},\"Property\":\"FY\"}}],\"Values\":[[{\"Literal\":{\"Value\":\"2025L\"}}]]}}}]},\"type\":\"Categorical\",\"howCreated\":1,\"objects\":{}}]",
          "height": 487.56,
          "width": 863.63,
          "x": 32.13,
          "y": 26.46,
          "z": 0.00
        }
      ],
      "width": 1280.00
    }
  ]
}